Workbook

Sheet Summary
B2: API Test Case Checklist
B3: Project: School Management ERP | Test Type: API Testing
B4: Prepared by: QA Lead | Date: ___________
B7: Total APIs | D7: Passed | F7: Failed | H7: Blocked | J7: Not Executed
B8: =COUNTA('API Test Cases'!A5:A1000) -> 80 | D8: =COUNTIF('API Test Cases'!J5:J1000,"Pass") -> 68 | F8: =COUNTIF('API Test Cases'!J5:J1000,"Fail") -> 12 | H8: =COUNTIF('API Test Cases'!J5:J1000,"Blocked") -> 0 | J8: =COUNTIF('API Test Cases'!J5:J1000,"Not Executed") -> 0
B11: Priority Breakdown | E11: Method Breakdown | H11: Module Count
B12: High | C12: =COUNTIF('API Test Cases'!I5:I1000,"High") -> 43 | E12: GET | F12: =COUNTIF('API Test Cases'!D5:D1000,"GET") -> 26 | H12: Authentication | I12: =COUNTIF('API Test Cases'!B5:B1000,"Authentication") -> 10
B13: Medium | C13: =COUNTIF('API Test Cases'!I5:I1000,"Medium") -> 37 | E13: POST | F13: =COUNTIF('API Test Cases'!D5:D1000,"POST") -> 48 | H13: Student | I13: =COUNTIF('API Test Cases'!B5:B1000,"Student") -> 9
B14: Low | C14: =COUNTIF('API Test Cases'!I5:I1000,"Low") -> 0 | E14: PUT | F14: =COUNTIF('API Test Cases'!D5:D1000,"PUT") -> 3 | H14: Admission | I14: =COUNTIF('API Test Cases'!B5:B1000,"Admission") -> 6
E15: DELETE | F15: =COUNTIF('API Test Cases'!D5:D1000,"DELETE") -> 3 | H15: Teacher | I15: =COUNTIF('API Test Cases'!B5:B1000,"Teacher") -> 5
H16: Attendance | I16: =COUNTIF('API Test Cases'!B5:B1000,"Attendance") -> 5
H17: Homework | I17: =COUNTIF('API Test Cases'!B5:B1000,"Homework") -> 5
H18: Examination | I18: =COUNTIF('API Test Cases'!B5:B1000,"Examination") -> 7
H19: Finance | I19: =COUNTIF('API Test Cases'!B5:B1000,"Finance") -> 5
H20: Accounts | I20: =COUNTIF('API Test Cases'!B5:B1000,"Accounts") -> 4
H21: Communication | I21: =COUNTIF('API Test Cases'!B5:B1000,"Communication") -> 3
H22: Library | I22: =COUNTIF('API Test Cases'!B5:B1000,"Library") -> 3
H23: Inventory | I23: =COUNTIF('API Test Cases'!B5:B1000,"Inventory") -> 3
H24: Transport | I24: =COUNTIF('API Test Cases'!B5:B1000,"Transport") -> 2
H25: Reports | I25: =COUNTIF('API Test Cases'!B5:B1000,"Reports") -> 4
H26: Security | I26: =COUNTIF('API Test Cases'!B5:B1000,"Security") -> 9

Sheet API Test Cases
A1: API Test Case Checklist — School Management ERP
A4: API ID | B4: Module | C4: API Name | D4: Method | E4: Test Scenario | F4: Test Data | G4: Expected Status Code | H4: Expected Result | I4: Priority | J4: Status
A5: API-001 | B5: Authentication | C5: Login | D5: POST | E5: Login with valid credentials | F5: Valid Email & Password | G5: 200 OK | H5: User logged in successfully and token generated | I5: High | J5: Fail
A6: API-002 | B6: Authentication | C6: Login | D6: POST | E6: Login with invalid password | F6: Valid Email + Invalid Password | G6: 401 Unauthorized | H6: Proper error message displayed | I6: High | J6: Pass
A7: API-003 | B7: Authentication | C7: Login | D7: POST | E7: Login with invalid email | F7: Invalid Email | G7: 401 Unauthorized | H7: Authentication failed | I7: High | J7: Pass
A8: API-004 | B8: Authentication | C8: Login | D8: POST | E8: Login with empty email | F8: Empty Email | G8: 400 Bad Request | H8: Email validation message | I8: High | J8: Pass
A9: API-005 | B9: Authentication | C9: Login | D9: POST | E9: Login with empty password | F9: Empty Password | G9: 400 Bad Request | H9: Password validation message | I9: High | J9: Pass
A10: API-006 | B10: Authentication | C10: Login | D10: POST | E10: Missing request body | F10: {} | G10: 400 Bad Request | H10: Request validation failed | I10: High | J10: Pass
A11: API-007 | B11: Authentication | C11: Login | D11: POST | E11: SQL Injection attempt | F11: ' OR 1=1 -- | G11: 400/401 | H11: Request rejected | I11: High | J11: Pass
A12: API-008 | B12: Authentication | C12: Login | D12: POST | E12: XSS payload | F12: <script>alert(1)</script> | G12: 400 | H12: Input sanitized | I12: Medium | J12: Fail
A13: API-009 | B13: Authentication | C13: Logout | D13: POST | E13: Logout with valid token | F13: Bearer Token | G13: 200 OK | H13: User logged out successfully | I13: Medium | J13: Pass
A14: API-010 | B14: Authentication | C14: Logout | D14: POST | E14: Logout with invalid token | F14: Invalid Token | G14: 401 Unauthorized | H14: Unauthorized response | I14: High | J14: Pass
A15: API-011 | B15: Student | C15: Student List | D15: GET | E15: Retrieve all students | F15: Valid Token | G15: 200 OK | H15: Student list returned | I15: High | J15: Pass
... A84: API-080 | B84: Security | C84: Server Error Handling | D84: GET | E84: Request invalid endpoint | F84: Invalid URL | G84: 404 Not Found | H84: Proper error response returned without exposing server information | I84: Medium | J84: Pass

Sheet Raw Test Data
A1: Raw API Test Case Data — All 80 Rows (Reference)
A2: API ID | B2: Module | C2: API Name | D2: Method | E2: Test Scenario | F2: Test Data | G2: Expected Status Code | H2: Expected Result | I2: Priority | J2: Status
A3: API-001 | B3: Authentication | C3: Login | D3: POST | E3: Login with valid credentials | F3: Valid Email & Password | G3: 200 OK | H3: User logged in successfully and token generated | I3: High | J3: Not Executed
A4: API-002 | B4: Authentication | C4: Login | D4: POST | E4: Login with invalid password | F4: Valid Email + Invalid Password | G4: 401 Unauthorized | H4: Proper error message displayed | I4: High | J4: Not Executed
A5: API-003 | B5: Authentication | C5: Login | D5: POST | E5: Login with invalid email | F5: Invalid Email | G5: 401 Unauthorized | H5: Authentication failed | I5: High | J5: Not Executed
A6: API-004 | B6: Authentication | C6: Login | D6: POST | E6: Login with empty email | F6: Empty Email | G6: 400 Bad Request | H6: Email validation message | I6: High | J6: Not Executed
A7: API-005 | B7: Authentication | C7: Login | D7: POST | E7: Login with empty password | F7: Empty Password | G7: 400 Bad Request | H7: Password validation message | I7: High | J7: Not Executed
A8: API-006 | B8: Authentication | C8: Login | D8: POST | E8: Missing request body | F8: {} | G8: 400 Bad Request | H8: Request validation failed | I8: High | J8: Not Executed
A9: API-007 | B9: Authentication | C9: Login | D9: POST | E9: SQL Injection attempt | F9: ' OR 1=1 -- | G9: 400/401 | H9: Request rejected | I9: High | J9: Not Executed
A10: API-008 | B10: Authentication | C10: Login | D10: POST | E10: XSS payload | F10: <script>alert(1)</script> | G10: 400 | H10: Input sanitized | I10: Medium | J10: Not Executed
A11: API-009 | B11: Authentication | C11: Logout | D11: POST | E11: Logout with valid token | F11: Bearer Token | G11: 200 OK | H11: User logged out successfully | I11: Medium | J11: Not Executed
A12: API-010 | B12: Authentication | C12: Logout | D12: POST | E12: Logout with invalid token | F12: Invalid Token | G12: 401 Unauthorized | H12: Unauthorized response | I12: High | J12: Not Executed
A13: API-011 | B13: Student | C13: Student List | D13: GET | E13: Retrieve all students | F13: Valid Token | G13: 200 OK | H13: Student list returned | I13: High | J13: Not Executed
... A82: API-080 | B82: Security | C82: Server Error Handling | D82: GET | E82: Request invalid endpoint | F82: Invalid URL | G82: 404 Not Found | H82: Proper error response returned without exposing server information | I82: Medium | J82: Not Executed
